clearskies_doc_builder/__init__.py
clearskies_doc_builder/build_callable.py
clearskies_doc_builder/prepare_doc_space.py
clearskies_doc_builder/backends/__init__.py
clearskies_doc_builder/backends/attribute_backend.py
clearskies_doc_builder/backends/class_backend.py
clearskies_doc_builder/backends/module_backend.py
clearskies_doc_builder/backends/python.py
clearskies_doc_builder/builders/__init__.py
clearskies_doc_builder/builders/builder.py
clearskies_doc_builder/builders/module.py
clearskies_doc_builder/builders/single_class.py
clearskies_doc_builder/builders/single_class_to_section.py
clearskies_doc_builder/columns/__init__.py
clearskies_doc_builder/columns/any.py
clearskies_doc_builder/columns/attribute.py
clearskies_doc_builder/columns/attributes.py
clearskies_doc_builder/columns/base_classes.py
clearskies_doc_builder/columns/class_column.py
clearskies_doc_builder/columns/method.py
clearskies_doc_builder/columns/module.py
clearskies_doc_builder/columns/module_classes.py
clearskies_doc_builder/configs/__init__.py
clearskies_doc_builder/models/__init__.py
clearskies_doc_builder/models/arg.py
clearskies_doc_builder/models/attribute.py
clearskies_doc_builder/models/attribute_reference.py
clearskies_doc_builder/models/class_model.py
clearskies_doc_builder/models/class_reference.py
clearskies_doc_builder/models/method.py
clearskies_doc_builder/models/method_reference.py
clearskies_doc_builder/models/module.py
clearskies_doc_builder/models/module_reference.py
clearskies_doc_builder/models/property.py
clear_skies_doc_builder-2.0.5.dist-info/METADATA
clear_skies_doc_builder-2.0.5.dist-info/WHEEL
clear_skies_doc_builder-2.0.5.dist-info/licenses/LICENSE
clear_skies_doc_builder-2.0.5.dist-info/RECORD
