Metadata-Version: 2.4
Name: clear-skies-doc-builder
Version: 2.0.5
Summary: The docbuilder for all 'official' clearskies plugins (as well as the main clearskies docs)
Project-URL: repository, https://github.com/clearskies-py/docs
Project-URL: issues, https://github.com/clearskies-py/docs/issues
Project-URL: changelog, https://github.com/clearskies-py/docs/blob/main/CHANGELOG.md
Author-email: Conor Mancone <cmancone@gmail.com>
License-Expression: MIT
License-File: LICENSE
Classifier: Development Status :: 5 - Production/Stable
Classifier: Intended Audience :: Developers
Classifier: License :: OSI Approved :: MIT License
Classifier: Programming Language :: Python :: 3
Requires-Python: <4.0,>=3.11
Requires-Dist: clear-skies<3.0.0,>=2.0.0
Provides-Extra: dev
Requires-Dist: types-requests>=2.32.4; extra == 'dev'
